ctlog.pyi
ctlog.cpython-37m-x86_64-linux-gnu.so
ctlog/alg/ca/ipog/nim_pool.cpython-37m-x86_64-linux-gnu.so
ctlog/alg/ca/prbot/nim_pool_mngr_naive.cpython-37m-x86_64-linux-gnu.so
ctlog/alg/ca/prbot/nim_pool_mngr.cpython-37m-x86_64-linux-gnu.so
ctlog/resources/ctlog.pem
ctlog/sut/nim_ts.cpython-37m-x86_64-linux-gnu.so
ctlog/sut/nim_tupls.cpython-37m-x86_64-linux-gnu.so
ctlog-0.6.0.dist-info/LICENSE
ctlog-0.6.0.dist-info/entry_points.txt
ctlog-0.6.0.dist-info/top_level.txt
ctlog-0.6.0.dist-info/RECORD
ctlog-0.6.0.dist-info/METADATA
ctlog-0.6.0.dist-info/WHEEL
