Metadata-Version: 2.1
Name: ctlog
Version: 0.6.0
Summary: SAT-Based Combinatorial Testing in Python
Home-page: http://ulog.udl.cat/software/
Author: Logic and Optimization Group
Author-email: 
Keywords: combinatorial-testing sat maxsat constraint
Platform: Linux
Classifier: Development Status :: 4 - Beta
Classifier: Intended Audience :: Developers
Classifier: Intended Audience :: Science/Research
Classifier: Natural Language :: English
Classifier: Programming Language :: Python :: 3
Classifier: Operating System :: POSIX :: Linux
Classifier: Topic :: Scientific/Engineering
Classifier: Topic :: Scientific/Engineering :: Artificial Intelligence
License-File: LICENSE
Requires-Dist: optilog (>=0.5.0)
Requires-Dist: nimporter (==1.1.0)
Requires-Dist: psutil
Requires-Dist: pyzlic
Requires-Dist: sly (==0.4)
